{
  "project_info": {
    "project_number": "392134002631",
    "project_id": "chat-application-453b4",
    "storage_bucket": "chat-application-453b4.appspot.com"
  },
  "client": [
    {
      "client_info": {
        "mobilesdk_app_id": "1:392134002631:android:0097456ceffcac6270fbe2",
        "android_client_info": {
          "package_name": "com.example.chat_a"
        }
      },
      "oauth_client": [],
      "api_key": [
        {
          "current_key": "AIzaSyAxZrMSoJbWvWaELjZbBMgo2Z8BuwusCGQ"
        }
      ],
      "services": {
        "appinvite_service": {
          "other_platform_oauth_client": []
        }
      }
    }
  ],
  "configuration_version": "1"
}